amberdata_api/__init__.py
amberdata_api/main.py
amberdata_api/schemas.py
amberdata_api-1.0.0.dist-info/METADATA
amberdata_api-1.0.0.dist-info/WHEEL
amberdata_api-1.0.0.dist-info/RECORD
